bevpo/__init__.py
bevpo/calc_tfsprop.py
bevpo/prob_dist.py
bevpo/samp_traf.py
bevpo/save_results.py
bevpo/trafficsystem.py
bevpo/datasets/__init__.py
bevpo/datasets/prep_ubermovement.py
bevpo-0.1.3.dist-info/METADATA
bevpo-0.1.3.dist-info/WHEEL
bevpo-0.1.3.dist-info/top_level.txt
bevpo-0.1.3.dist-info/RECORD
