Metadata-Version: 2.1
Name: bevpo
Version: 0.1.3
Summary: City-scale car traffic and parking analysis tool
Home-page: UNKNOWN
Author: Arsam Aryandoust
Author-email: arsama@ethz.ch
License: UNKNOWN
Project-URL: Code repository, https://github.com/ArsamAryandoust/bevpo
Platform: UNKNOWN
Classifier: Programming Language :: Python :: 3
Classifier: License :: OSI Approved :: MIT License
Classifier: Operating System :: OS Independent
Requires-Dist: numpy (>=1.20.0)
Requires-Dist: pandas (>=1.3.0)
Requires-Dist: matplotlib (>=3.4.0)
Requires-Dist: imageio (>=2.9.0)
